Workbook
Name Product_List: 'Inputs'!$B$6:$B$10
Name Std_Price_Unit: 'Inputs'!$C$6:$C$10
Name Std_Qty: 'Inputs'!$D$6:$D$10
Name Std_Labor_Rate: 'Inputs'!$E$6:$E$10
Name Std_Labor_Hours: 'Inputs'!$F$6:$F$10
Name Std_Var_OH_Rate_Hr: 'Inputs'!$G$6:$G$10
Name Budgeted_Fixed_OH: 'Inputs'!$H$6:$H$10
Name Std_Fixed_OH_Rate_Hr: 'Inputs'!$I$6:$I$10
Name Budgeted_Selling_Price: 'Inputs'!$J$6:$J$10
Name Budgeted_Units: 'Inputs'!$K$6:$K$10
Name MI_Product: 'Inputs'!$B$15:$B$21
Name MI_Material: 'Inputs'!$C$15:$C$21
Name MI_Std_Price: 'Inputs'!$D$15:$D$21
Name MI_Std_Qty: 'Inputs'!$E$15:$E$21
Name MI_Actual_Price: 'Inputs'!$F$15:$F$21
Name MI_Actual_Qty: 'Inputs'!$G$15:$G$21
Name Actual_Product: 'Actuals'!$B$6:$B$10
Name Actual_Price: 'Actuals'!$C$6:$C$10
Name Actual_Qty: 'Actuals'!$D$6:$D$10
Name Actual_Labor_Rate: 'Actuals'!$E$6:$E$10
Name Actual_Labor_Hours: 'Actuals'!$F$6:$F$10
Name Actual_Var_OH: 'Actuals'!$G$6:$G$10
Name Actual_Fixed_OH: 'Actuals'!$H$6:$H$10
Name Actual_Selling_Price: 'Actuals'!$I$6:$I$10
Name Actual_Units: 'Actuals'!$J$6:$J$10

Sheet Read Me
B2: KM Consulting — Standard Costing Variance Model
B3: Version v1.0 | Formula-only workbook | Excel 2016+
B4: Topic | C4: Detail
B5: Purpose | C5: Calculate standard-costing variances, sales variances, overhead variances, and an operating-profit bridge.
B6: How to use | C6: Enter assumptions on Inputs and actual results on Actuals. Calc and Dashboard are formula-driven and protected.
B7: Sign convention | C7: Positive variance = Unfavorable = actual cost above standard or sales below budget; negative = Favorable.
B8: Assumptions | C8: Fixed OH absorption costing. Overhead activity base = labor hours. Material mix/yield supports multiple materials per product.
B9: Version | C9: v1.0

Sheet Inputs
B2: Inputs
B3: Blue cells are editable. Named ranges are applied to table columns.
B4: Products
B5: Product | C5: Std price/unit | D5: Std qty | E5: Std labor rate | F5: Std labor hours | G5: Std var OH rate/hr | H5: Budgeted fixed OH | I5: Std fixed OH rate/hr | J5: Budgeted selling price | K5: Budgeted units
B6: Product A | C6: 5 | D6: 3000 | E6: 20 | F6: 2000 | G6: 4 | H6: 11000 | I6: 5 | J6: 35 | K6: 100
B7: Product B | C7: 8 | D7: 1000 | E7: 25 | F7: 750 | G7: 6 | H7: 6000 | I7: 8 | J7: 50 | K7: 80
B8: Product C | C8: 6.5 | D8: 0 | E8: 22 | F8: 0 | G8: 5 | H8: 0 | I8: 6 | J8: 40 | K8: 0
B9: Product D | C9: 9 | D9: 0 | E9: 24 | F9: 0 | G9: 6 | H9: 0 | I9: 7 | J9: 55 | K9: 0
B10: Product E | C10: 4.25 | D10: 0 | E10: 18 | F10: 0 | G10: 3 | H10: 0 | I10: 4 | J10: 30 | K10: 0
B13: Material Inputs
B14: Product | C14: Material | D14: Std price | E14: Std qty | F14: Actual price | G14: Actual qty
B15: Product A | C15: Material 1 | D15: 5 | E15: 3000 | F15: 5.2 | G15: 3200
B16: Product B | C16: Material 1 | D16: 8 | E16: 1000 | F16: 7.8 | G16: 1050
B17: Product A | C17: Material 2 | D17: 0 | E17: 0 | F17: 0 | G17: 0
B18: Product B | C18: Material 2 | D18: 0 | E18: 0 | F18: 0 | G18: 0
B19: Product C | C19: Material 1 | D19: 0 | E19: 0 | F19: 0 | G19: 0
B20: Product D | C20: Material 1 | D20: 0 | E20: 0 | F20: 0 | G20: 0
B21: Product E | C21: Material 1 | D21: 0 | E21: 0 | F21: 0 | G21: 0

Sheet Actuals
B2: Actuals
B3: Enter actual cost and sales data by product.
B5: Product | C5: Actual price | D5: Actual qty | E5: Actual labor rate | F5: Actual labor hours | G5: Actual var OH | H5: Actual fixed OH | I5: Actual selling price | J5: Actual units
B6: Product A | C6: 5.2 | D6: 3200 | E6: 19.5 | F6: 2100 | G6: 8600 | H6: 11300 | I6: 36 | J6: 105
B7: Product B | C7: 7.8 | D7: 1050 | E7: 25.4 | F7: 720 | G7: 4700 | H7: 5900 | I7: 48 | J7: 78
B8: Product C | C8: 0 | D8: 0 | E8: 0 | F8: 0 | G8: 0 | H8: 0 | I8: 0 | J8: 0
B9: Product D | C9: 0 | D9: 0 | E9: 0 | F9: 0 | G9: 0 | H9: 0 | I9: 0 | J9: 0
B10: Product E | C10: 0 | D10: 0 | E10: 0 | F10: 0 | G10: 0 | H10: 0 | I10: 0 | J10: 0

Sheet Calc
B2: Variance Calculations
B3: Positive = Unfavorable; Negative = Favorable
B5: Product | C5: Std Mat Cost | D5: Act Mat Cost | E5: Material Price | F5: Material Quantity | G5: Material Mix | H5: Material Yield | I5: Labor Rate | J5: Labor Efficiency | K5: Labor Mix | L5: Var OH Spending | M5: Var OH Efficiency | N5: Fixed OH Budget | O5: Fixed OH Volume | P5: Sales Price | Q5: Sales Volume | R5: Sales Mix | S5: Total Cost Variance | T5: Sales Variance
B6: =Inputs!B6 | C6: =Inputs!C6*Inputs!D6 | D6: =Actuals!C6*Actuals!D6 | E6: =SUMPRODUCT((MI_Product=B6)*(MI_Actual_Price-MI_Std_Price)*MI_Actual_Qty) | F6: =SUMPRODUCT((MI_Product=B6)*(MI_Actual_Qty-MI_Std_Qty)*MI_Std_Price) | G6: =IFERROR(SUMPRODUCT((MI_Product=B6)*(MI_Actual_Qty-SUMIF(MI_Product,B6,MI_Actual_Qty)*MI_Std_Qty/SUMIF(MI_Product,B6,MI_Std_Qty))*MI_Std_Price),0) | H6: =F6-G6 | I6: =(Actuals!E6-Inputs!E6)*Actuals!F6 | J6: =(Actuals!F6-Inputs!F6)*Inputs!E6 | K6: =0 | L6: =Actuals!G6-Inputs!G6*Actuals!F6 | M6: =(Actuals!F6-Inputs!F6)*Inputs!G6 | N6: =Actuals!H6-Inputs!H6 | O6: =Inputs!H6-(Inputs!I6*Inputs!F6) | P6: =-(Actuals!I6-Inputs!J6)*Actuals!J6 | Q6: =-(Actuals!J6-Inputs!K6)*Inputs!J6 | R6: =0 | S6: =SUM(E6:O6) | T6: =SUM(P6:R6)
B7: =Inputs!B7 | C7: =Inputs!C7*Inputs!D7 | D7: =Actuals!C7*Actuals!D7 | E7: =SUMPRODUCT((MI_Product=B7)*(MI_Actual_Price-MI_Std_Price)*MI_Actual_Qty) | F7: =SUMPRODUCT((MI_Product=B7)*(MI_Actual_Qty-MI_Std_Qty)*MI_Std_Price) | G7: =IFERROR(SUMPRODUCT((MI_Product=B7)*(MI_Actual_Qty-SUMIF(MI_Product,B7,MI_Actual_Qty)*MI_Std_Qty/SUMIF(MI_Product,B7,MI_Std_Qty))*MI_Std_Price),0) | H7: =F7-G7 | I7: =(Actuals!E7-Inputs!E7)*Actuals!F7 | J7: =(Actuals!F7-Inputs!F7)*Inputs!E7 | K7: =0 | L7: =Actuals!G7-Inputs!G7*Actuals!F7 | M7: =(Actuals!F7-Inputs!F7)*Inputs!G7 | N7: =Actuals!H7-Inputs!H7 | O7: =Inputs!H7-(Inputs!I7*Inputs!F7) | P7: =-(Actuals!I7-Inputs!J7)*Actuals!J7 | Q7: =-(Actuals!J7-Inputs!K7)*Inputs!J7 | R7: =0 | S7: =SUM(E7:O7) | T7: =SUM(P7:R7)
B8: =Inputs!B8 | C8: =Inputs!C8*Inputs!D8 | D8: =Actuals!C8*Actuals!D8 | E8: =SUMPRODUCT((MI_Product=B8)*(MI_Actual_Price-MI_Std_Price)*MI_Actual_Qty) | F8: =SUMPRODUCT((MI_Product=B8)*(MI_Actual_Qty-MI_Std_Qty)*MI_Std_Price) | G8: =IFERROR(SUMPRODUCT((MI_Product=B8)*(MI_Actual_Qty-SUMIF(MI_Product,B8,MI_Actual_Qty)*MI_Std_Qty/SUMIF(MI_Product,B8,MI_Std_Qty))*MI_Std_Price),0) | H8: =F8-G8 | I8: =(Actuals!E8-Inputs!E8)*Actuals!F8 | J8: =(Actuals!F8-Inputs!F8)*Inputs!E8 | K8: =0 | L8: =Actuals!G8-Inputs!G8*Actuals!F8 | M8: =(Actuals!F8-Inputs!F8)*Inputs!G8 | N8: =Actuals!H8-Inputs!H8 | O8: =Inputs!H8-(Inputs!I8*Inputs!F8) | P8: =-(Actuals!I8-Inputs!J8)*Actuals!J8 | Q8: =-(Actuals!J8-Inputs!K8)*Inputs!J8 | R8: =0 | S8: =SUM(E8:O8) | T8: =SUM(P8:R8)
B9: =Inputs!B9 | C9: =Inputs!C9*Inputs!D9 | D9: =Actuals!C9*Actuals!D9 | E9: =SUMPRODUCT((MI_Product=B9)*(MI_Actual_Price-MI_Std_Price)*MI_Actual_Qty) | F9: =SUMPRODUCT((MI_Product=B9)*(MI_Actual_Qty-MI_Std_Qty)*MI_Std_Price) | G9: =IFERROR(SUMPRODUCT((MI_Product=B9)*(MI_Actual_Qty-SUMIF(MI_Product,B9,MI_Actual_Qty)*MI_Std_Qty/SUMIF(MI_Product,B9,MI_Std_Qty))*MI_Std_Price),0) | H9: =F9-G9 | I9: =(Actuals!E9-Inputs!E9)*Actuals!F9 | J9: =(Actuals!F9-Inputs!F9)*Inputs!E9 | K9: =0 | L9: =Actuals!G9-Inputs!G9*Actuals!F9 | M9: =(Actuals!F9-Inputs!F9)*Inputs!G9 | N9: =Actuals!H9-Inputs!H9 | O9: =Inputs!H9-(Inputs!I9*Inputs!F9) | P9: =-(Actuals!I9-Inputs!J9)*Actuals!J9 | Q9: =-(Actuals!J9-Inputs!K9)*Inputs!J9 | R9: =0 | S9: =SUM(E9:O9) | T9: =SUM(P9:R9)
B10: =Inputs!B10 | C10: =Inputs!C10*Inputs!D10 | D10: =Actuals!C10*Actuals!D10 | E10: =SUMPRODUCT((MI_Product=B10)*(MI_Actual_Price-MI_Std_Price)*MI_Actual_Qty) | F10: =SUMPRODUCT((MI_Product=B10)*(MI_Actual_Qty-MI_Std_Qty)*MI_Std_Price) | G10: =IFERROR(SUMPRODUCT((MI_Product=B10)*(MI_Actual_Qty-SUMIF(MI_Product,B10,MI_Actual_Qty)*MI_Std_Qty/SUMIF(MI_Product,B10,MI_Std_Qty))*MI_Std_Price),0) | H10: =F10-G10 | I10: =(Actuals!E10-Inputs!E10)*Actuals!F10 | J10: =(Actuals!F10-Inputs!F10)*Inputs!E10 | K10: =0 | L10: =Actuals!G10-Inputs!G10*Actuals!F10 | M10: =(Actuals!F10-Inputs!F10)*Inputs!G10 | N10: =Actuals!H10-Inputs!H10 | O10: =Inputs!H10-(Inputs!I10*Inputs!F10) | P10: =-(Actuals!I10-Inputs!J10)*Actuals!J10 | Q10: =-(Actuals!J10-Inputs!K10)*Inputs!J10 | R10: =0 | S10: =SUM(E10:O10) | T10: =SUM(P10:R10)
B11: Grand Total | C11: =SUM(C6:C10) | D11: =SUM(D6:D10) | E11: =SUM(E6:E10) | F11: =SUM(F6:F10) | G11: =SUM(G6:G10) | H11: =SUM(H6:H10) | I11: =SUM(I6:I10) | J11: =SUM(J6:J10) | ... T11: =SUM(T6:T10)

Sheet Dashboard
B2: Dashboard
B3: Operating-profit bridge and variance KPI summary
B4: Operating Profit Bridge | C4: Amount
B5: Budgeted operating profit | C5: =SUMPRODUCT(Budgeted_Selling_Price,Budgeted_Units)-SUMPRODUCT(Std_Price_Unit,Std_Qty)-SUMPRODUCT(Std_Labor_Rate,Std_Labor_Hours)-SUMPRODUCT(Std_Var_OH_Rate_Hr,Std_Labor_Hours)-SUMPRODUCT(Std_Fixed_OH_Rate_Hr,Std_Labor_Hours)
B6: Sales price variance | C6: =-Calc!P11
B7: Sales volume variance | C7: =-Calc!Q11
B8: Sales mix variance | C8: =-Calc!R11
B9: Cost variances | C9: =-Calc!S11
B10: Actual operating profit | C10: =SUM(C5:C9)
B15: Variance | C15: Amount | D15: F/U | E15: % of Standard
B16: Material | C16: =SUM(Calc!E11:H11) | D16: =IF(C16>0,"Unfavorable",IF(C16<0,"Favorable","Neutral")) | E16: =IFERROR(C16/(Calc!C11),0)
B17: Labor | C17: =SUM(Calc!I11:K11) | D17: =IF(C17>0,"Unfavorable",IF(C17<0,"Favorable","Neutral")) | E17: =IFERROR(C17/(SUMPRODUCT(Std_Labor_Rate,Std_Labor_Hours)),0)
B18: Variable OH | C18: =SUM(Calc!L11:M11) | D18: =IF(C18>0,"Unfavorable",IF(C18<0,"Favorable","Neutral")) | E18: =IFERROR(C18/(SUMPRODUCT(Std_Var_OH_Rate_Hr,Std_Labor_Hours)),0)
B19: Fixed OH | C19: =SUM(Calc!N11:O11) | D19: =IF(C19>0,"Unfavorable",IF(C19<0,"Favorable","Neutral")) | E19: =IFERROR(C19/(SUMPRODUCT(Std_Fixed_OH_Rate_Hr,Std_Labor_Hours)),0)
B20: Sales | C20: =Calc!T11 | D20: =IF(C20>0,"Unfavorable",IF(C20<0,"Favorable","Neutral")) | E20: =IFERROR(C20/(SUMPRODUCT(Budgeted_Selling_Price,Budgeted_Units)),0)
B24: Cost Reconciliation | C24: Amount
B25: Standard cost | C25: =SUMPRODUCT(Std_Price_Unit,Std_Qty)+SUMPRODUCT(Std_Labor_Rate,Std_Labor_Hours)+SUMPRODUCT(Std_Var_OH_Rate_Hr,Std_Labor_Hours)+SUMPRODUCT(Std_Fixed_OH_Rate_Hr,Std_Labor_Hours)
B26: Actual cost | C26: =SUMPRODUCT(Actual_Price,Actual_Qty)+SUMPRODUCT(Actual_Labor_Rate,Actual_Labor_Hours)+SUM(Actual_Var_OH)+SUM(Actual_Fixed_OH)
B27: Total cost variance | C27: =C26-C25

Sheet Example
B2: Worked Example — Two Product Single-Material Case
B3: Matches the requested cost-side grand totals.
B5: Product | C5: Std price | D5: Std qty | E5: Actual price | F5: Actual qty | G5: Std labor rate | H5: Std labor hours | I5: Actual labor rate | J5: Actual labor hours | K5: Std var OH rate | L5: Actual var OH | M5: Budgeted fixed OH | N5: Std fixed OH rate | O5: Actual fixed OH
B6: Product A | C6: 5 | D6: 3000 | E6: 5.2 | F6: 3200 | G6: 20 | H6: 2000 | I6: 19.5 | J6: 2100 | K6: 4 | L6: 8600 | M6: 11000 | N6: 5 | O6: 11300
B7: Product B | C7: 8 | D7: 1000 | E7: 7.8 | F7: 1050 | G7: 25 | H7: 750 | I7: 25.4 | J7: 720 | K7: 6 | L7: 4700 | M7: 6000 | N7: 8 | O7: 5900
B11: Product | C11: Std Cost | D11: Actual Cost | E11: Material Price | F11: Material Qty | G11: Labor Rate | H11: Labor Eff | I11: Var OH Spend | J11: Var OH Eff | K11: Fixed Budget | L11: Fixed Volume | M11: Total Cost Variance
B12: =B6 | C12: =C6*D6+G6*H6+K6*H6+N6*H6 | D12: =E6*F6+I6*J6+L6+O6 | E12: =(E6-C6)*F6 | F12: =(F6-D6)*C6 | G12: =(I6-G6)*J6 | H12: =(J6-H6)*G6 | I12: =L6-K6*J6 | J12: =(J6-H6)*K6 | K12: =O6-M6 | L12: =M6-N6*H6 | M12: =SUM(E12:L12)
B13: =B7 | C13: =C7*D7+G7*H7+K7*H7+N7*H7 | D13: =E7*F7+I7*J7+L7+O7 | E13: =(E7-C7)*F7 | F13: =(F7-D7)*C7 | G13: =(I7-G7)*J7 | H13: =(J7-H7)*G7 | I13: =L7-K7*J7 | J13: =(J7-H7)*K7 | K13: =O7-M7 | L13: =M7-N7*H7 | M13: =SUM(E13:L13)
B14: Grand Total | C14: =SUM(C12:C13) | D14: =SUM(D12:D13) | E14: =SUM(E12:E13) | F14: =SUM(F12:F13) | G14: =SUM(G12:G13) | H14: =SUM(H12:H13) | I14: =SUM(I12:I13) | J14: =SUM(J12:J13) | ... M14: =SUM(M12:M13)
B18: Standard cost | C18: =C14
B19: Actual cost | C19: =D14
B20: Total cost variance | C20: =M14 | D20: =IF(C20>0,"Unfavorable",IF(C20<0,"Favorable","Neutral"))
B22: Required check | C22: =AND(C18=110250,C19=114568,C20=4318) | D22: TRUE means the example totals match the specification.
