Workbook
Name StartCash: Inputs_CashFlow!$B$2

Sheet Cover
A1: Small-Business Cash Flow & Runway Starter
A2: Know exactly how many months of cash you have left.
A4: Free edition · Version 1.0 · 2026
A6: © KM Consulting · keystone.marcy@outlook.com · keystonemarcy.netlify.app
A8: Free to use for your own business. Redistribution or resale prohibited. See LICENSE.

Sheet How_to_Use
A1: How to Use This Tracker
A3: 1. On Inputs_CashFlow, replace the sample inflow and outflow rows with your own categories (keep the column headers).
A4: 2. Enter your starting cash in Inputs_CashFlow cell B2.
A5: 3. Fill in your expected monthly amounts for the next 12 months.
A6: 4. Read the Runway sheet to see your projected balance and months-of-cash-left.
A7: 5. Use the Scenarios sheet to stress-test Lean and Growth cases.
A9: Want weekly (13-week) precision and automatic bank-statement import? Upgrade — see the Upgrade sheet.

Sheet Inputs_CashFlow
A1: Cash Flow Inputs (12 months)
A2: Starting Cash: | B2: 50000
A4: Category | B4: Type | C4: Month 1 | D4: Month 2 | E4: Month 3 | F4: Month 4 | G4: Month 5 | H4: Month 6 | I4: Month 7 | J4: Month 8 | K4: Month 9 | L4: Month 10 | M4: Month 11 | N4: Month 12
A5: CASH IN
A6: Product Sales | B6: Inflow | C6: 30000 | D6: 31000 | E6: 32000 | F6: 33000 | G6: 34000 | H6: 35000 | I6: 36000 | J6: 37000 | K6: 38000 | L6: 39000 | M6: 39500 | N6: 40000
A7: Services / Recurring | B7: Inflow | C7: 12000 | D7: 12000 | E7: 12000 | F7: 12000 | G7: 12000 | H7: 12000 | I7: 12000 | J7: 12000 | K7: 12000 | L7: 12000 | M7: 12000 | N7: 12000
A8: Other Income | B8: Inflow | C8: 1500 | D8: 1500 | E8: 1500 | F8: 1500 | G8: 1500 | H8: 1500 | I8: 1500 | J8: 1500 | K8: 1500 | L8: 1500 | M8: 1500 | N8: 1500
A9: Owner / Loan Injection | B9: Inflow | C9: 20000 | D9: 0 | E9: 0 | F9: 0 | G9: 0 | H9: 0 | I9: 0 | J9: 0 | K9: 0 | L9: 0 | M9: 0 | N9: 0
A11: CASH OUT
A12: Payroll | B12: Outflow | C12: 22000 | D12: 22000 | E12: 22000 | F12: 22000 | G12: 22000 | H12: 22000 | I12: 22000 | J12: 22000 | K12: 22000 | L12: 22000 | M12: 22000 | N12: 22000
A13: Rent & Utilities | B13: Outflow | C13: 4500 | D13: 4500 | E13: 4500 | F13: 4500 | G13: 4500 | H13: 4500 | I13: 4500 | J13: 4500 | K13: 4500 | L13: 4500 | M13: 4500 | N13: 4500
A14: Inventory / COGS | B14: Outflow | C14: 12000 | D14: 12000 | E14: 12000 | F14: 12000 | G14: 12000 | H14: 12000 | I14: 12000 | J14: 12000 | K14: 12000 | L14: 12000 | M14: 12000 | N14: 12000
A15: Marketing | B15: Outflow | C15: 3000 | D15: 3000 | E15: 3000 | F15: 3000 | G15: 3000 | H15: 3000 | I15: 3000 | J15: 3000 | K15: 3000 | L15: 3000 | M15: 3000 | N15: 3000
A16: Software & Tools | B16: Outflow | C16: 1200 | D16: 1200 | E16: 1200 | F16: 1200 | G16: 1200 | H16: 1200 | I16: 1200 | J16: 1200 | K16: 1200 | L16: 1200 | M16: 1200 | N16: 1200
A17: Loan Repayment | B17: Outflow | C17: 2000 | D17: 2000 | E17: 2000 | F17: 2000 | G17: 2000 | H17: 2000 | I17: 2000 | J17: 2000 | K17: 2000 | L17: 2000 | M17: 2000 | N17: 2000
A18: Taxes | B18: Outflow | C18: 0 | D18: 0 | E18: 3500 | F18: 0 | G18: 0 | H18: 3500 | I18: 0 | J18: 0 | K18: 3500 | L18: 0 | M18: 0 | N18: 3500
A19: Other Expenses | B19: Outflow | C19: 1000 | D19: 1000 | E19: 1000 | F19: 1000 | G19: 1000 | H19: 1000 | I19: 1000 | J19: 1000 | K19: 1000 | L19: 1000 | M19: 1000 | N19: 1000
A21: NET CASH FLOW | C21: =SUM(C6:C9)-SUM(C12:C19) | D21: =SUM(D6:D9)-SUM(D12:D19) | E21: =SUM(E6:E9)-SUM(E12:E19) | F21: =SUM(F6:F9)-SUM(F12:F19) | G21: =SUM(G6:G9)-SUM(G12:G19) | H21: =SUM(H6:H9)-SUM(H12:H19) | I21: =SUM(I6:I9)-SUM(I12:I19) | J21: =SUM(J6:J9)-SUM(J12:J19) | ... N21: =SUM(N6:N9)-SUM(N12:N19)
A23: Enter all outflows as POSITIVE numbers. Replace sample rows with your own - keep the Type column as Inflow or Outflow.

Sheet Runway
A1: Runway & Ending Cash Projection
A3: Metric | B3: Month 1 | C3: Month 2 | D3: Month 3 | E3: Month 4 | F3: Month 5 | G3: Month 6 | H3: Month 7 | I3: Month 8 | J3: Month 9 | K3: Month 10 | L3: Month 11 | M3: Month 12
A4: Net Cash Flow | B4: =Inputs_CashFlow!C21 | C4: =Inputs_CashFlow!D21 | D4: =Inputs_CashFlow!E21 | E4: =Inputs_CashFlow!F21 | F4: =Inputs_CashFlow!G21 | G4: =Inputs_CashFlow!H21 | H4: =Inputs_CashFlow!I21 | I4: =Inputs_CashFlow!J21 | ... M4: =Inputs_CashFlow!N21
A5: Ending Cash | B5: =Inputs_CashFlow!B2+B4 | C5: =B5+C4 | D5: =C5+D4 | E5: =D5+E4 | F5: =E5+F4 | G5: =F5+G4 | H5: =G5+H4 | I5: =H5+I4 | J5: =I5+J4 | ... M5: =L5+M4
A6: Cash-Out This Month | B6: =SUM(Inputs_CashFlow!C12:C19) | C6: =SUM(Inputs_CashFlow!D12:D19) | D6: =SUM(Inputs_CashFlow!E12:E19) | E6: =SUM(Inputs_CashFlow!F12:F19) | F6: =SUM(Inputs_CashFlow!G12:G19) | G6: =SUM(Inputs_CashFlow!H12:H19) | H6: =SUM(Inputs_CashFlow!I12:I19) | I6: =SUM(Inputs_CashFlow!J12:J19) | ... M6: =SUM(Inputs_CashFlow!N12:N19)
A8: Average Monthly Net Burn: | B8: =-AVERAGE(B4:M4) | C8: (positive = burning cash)
A9: Months of Cash Left (from today): | B9: =IF(B8<=0,"Cash-flow positive — no runway limit",Inputs_CashFlow!B2/B8)
A11: First month projected to go negative: | B11: =IFERROR(INDEX($B$3:$M$3,MATCH(1,$B$13:$M$13,0)),"None in 12-month window")
B13: =IF(B5<0,1,0) | C13: =IF(C5<0,1,0) | D13: =IF(D5<0,1,0) | E13: =IF(E5<0,1,0) | F13: =IF(F5<0,1,0) | G13: =IF(G5<0,1,0) | H13: =IF(H5<0,1,0) | I13: =IF(I5<0,1,0) | ... M13: =IF(M5<0,1,0)

Sheet Scenarios
A1: Scenario Stress Test | G1: helpers
G2: =SUM(Inputs_CashFlow!C6:N9)
A3: Assumptions | G3: =SUM(Inputs_CashFlow!C12:N19)
A4: Scenario | B4: Inflow x | C4: Outflow x | D4: Months of Cash Left
A5: Base | B5: 1 | C5: 1 | D5: =IF((($G$3*C5)-($G$2*B5))/12<=0,"Positive",Inputs_CashFlow!$B$2/((($G$3*C5)-($G$2*B5))/12))
A6: Lean (revenue -20%, costs -10%) | B6: 0.8 | C6: 0.9 | D6: =IF((($G$3*C6)-($G$2*B6))/12<=0,"Positive",Inputs_CashFlow!$B$2/((($G$3*C6)-($G$2*B6))/12))
A7: Growth (revenue +25%, costs +15%) | B7: 1.25 | C7: 1.15 | D7: =IF((($G$3*C7)-($G$2*B7))/12<=0,"Positive",Inputs_CashFlow!$B$2/((($G$3*C7)-($G$2*B7))/12))
A9: This is a simplified annualized stress test. For weekly precision and bank-import-driven actuals, see the 13-Week Forecast (Upgrade sheet).

Sheet Upgrade
A1: Ready for the next level?
A3: This free tracker gives you a monthly view. When you need weekly precision, one-click import of your bank / AR / AP exports, covenant tracking, and forecast-vs-actual variance, upgrade to the 13-Week Direct Cash Flow Forecast.
A5: Get the 13-Week Forecast: https://keystonemarcy.netlify.app/templates.html
A7: Need hands-on help? KM Consulting offers fractional FP&A. Contact keystone.marcy@outlook.com.
